k7/__init__.py
k7/__version__.py
k7/k7.py
k7/utils.py
k7-0.4.2.dist-info/METADATA
k7-0.4.2.dist-info/RECORD
k7-0.4.2.dist-info/WHEEL
k7-0.4.2.dist-info/top_level.txt
