Metadata-Version: 2.1
Name: k7
Version: 0.4.2
Summary: Manipulate k7 files with one hand
Home-page: http://github.com/keomabrun/k7
Author: Keoma Brun-Laguna
Author-email: contact@kbl.netlib.re
License: GPL
Platform: UNKNOWN
Classifier: Programming Language :: Python :: 2.7
Classifier: Programming Language :: Python :: 3
Requires-Dist: pandas
